aim2dat/__init__.py
aim2dat/aiida_data/__init__.py
aim2dat/aiida_data/gaussian_cube_data.py
aim2dat/aiida_data/surface_data.py
aim2dat/aiida_workflows/__init__.py
aim2dat/aiida_workflows/_workflow_builder_utils.py
aim2dat/aiida_workflows/utils.py
aim2dat/aiida_workflows/workflow_builder.py
aim2dat/aiida_workflows/chargemol/__init__.py
aim2dat/aiida_workflows/chargemol/calcjobs.py
aim2dat/aiida_workflows/chargemol/parsers.py
aim2dat/aiida_workflows/cp2k/__init__.py
aim2dat/aiida_workflows/cp2k/auxiliary_functions.py
aim2dat/aiida_workflows/cp2k/band_structure_work_chain.py
aim2dat/aiida_workflows/cp2k/base_core_work_chain.py
aim2dat/aiida_workflows/cp2k/base_opt_work_chain.py
aim2dat/aiida_workflows/cp2k/calcjobs.py
aim2dat/aiida_workflows/cp2k/cell_opt_work_chain.py
aim2dat/aiida_workflows/cp2k/combined_work_chains.py
aim2dat/aiida_workflows/cp2k/core_work_chain_handlers.py
aim2dat/aiida_workflows/cp2k/core_work_chain_inputs.py
aim2dat/aiida_workflows/cp2k/core_work_chain_opt.py
aim2dat/aiida_workflows/cp2k/core_work_chain_scf.py
aim2dat/aiida_workflows/cp2k/cube_work_chain.py
aim2dat/aiida_workflows/cp2k/eigenvalues_work_chain.py
aim2dat/aiida_workflows/cp2k/el_properties_utils.py
aim2dat/aiida_workflows/cp2k/find_scf_p_work_chain.py
aim2dat/aiida_workflows/cp2k/geo_opt_work_chain.py
aim2dat/aiida_workflows/cp2k/interaction_energy_work_chain.py
aim2dat/aiida_workflows/cp2k/parsers.py
aim2dat/aiida_workflows/cp2k/partial_charges_work_chain.py
aim2dat/aiida_workflows/cp2k/pdos_work_chain.py
aim2dat/aiida_workflows/cp2k/planar_fields_work_chain.py
aim2dat/aiida_workflows/cp2k/surface_opt_utils.py
aim2dat/aiida_workflows/cp2k/work_chain_specs.py
aim2dat/aiida_workflows/cp2k/opt_parameter_files/cell_opt_p.yaml
aim2dat/aiida_workflows/cp2k/opt_parameter_files/geo_opt_p.yaml
aim2dat/aiida_workflows/cp2k/parameter_files/basis_sets.yaml
aim2dat/aiida_workflows/cp2k/parameter_files/xc_functionals_p.yaml
aim2dat/aiida_workflows/cp2k/scf_parameter_files/density_mixing_p.yaml
aim2dat-0.4.0.dist-info/licenses/LICENSE
aim2dat-0.4.0.dist-info/METADATA
aim2dat-0.4.0.dist-info/WHEEL
aim2dat-0.4.0.dist-info/entry_points.txt
aim2dat-0.4.0.dist-info/top_level.txt
aim2dat-0.4.0.dist-info/RECORD
